[
  {
    "id": 1,
    "type": "Job Offer",
    "fieldOfStudy": "Software Engineering",
    "title": "Frontend Developer",
    "company": "Deutsche Telekom",
    "location": "Berlin",
    "description": "Lorem ipsum dolor sit amet, consectetur adipiscing elit. Nullam in varius nulla.",
    "qualificationsAndRequirements": "Lorem ipsum dolor sit amet, consectetur adipiscing elit.",
    "tags": ["JavaScript", "React", "CSS"],
    "experienceRequired": "Junior",
    "engagementType": "Full-time",
    "workArrangement": "Remote",
    "endingDate": "2024-12-12",
    "benefits": "Lorem ipsum dolor sit amet, consectetur adipiscing elit.",
    "employeeInfo": "Lorem ipsum dolor sit amet, consectetur adipiscing elit.",
    "contactPerson": "Jane Doe",
    "contactPersonEmail": "jane.doe@telekom.com"
  },
  {
    "id": 2,
    "type": "Internship",
    "fieldOfStudy": "Artificial Intelligence and Data Engineering",
    "title": "Data Science Intern",
    "company": "Deutsche Telekom",
    "location": "Sarajevo",
    "description": "Lorem ipsum dolor sit amet, consectetur adipiscing elit. Fusce euismod.",
    "qualificationsAndRequirements": "Lorem ipsum dolor sit amet, consectetur adipiscing elit.",
    "tags": ["Python", "ML", "Big Data"],
    "experienceRequired": "Intern",
    "engagementType": "Part-time",
    "workArrangement": "Hybrid",
    "endingDate": "2025-01-15",
    "benefits": "Lorem ipsum dolor sit amet, consectetur adipiscing elit.",
    "employeeInfo": "Lorem ipsum dolor sit amet, consectetur adipiscing elit.",
    "contactPerson": "John Smith",
    "contactPersonEmail": "john.smith@telekom.com"
  },
  {
    "id": 3,
    "type": "Thesis Topic",
    "fieldOfStudy": "Electrical and Electronics Engineering",
    "title": "IoT for Smart Cities",
    "company": "Deutsche Telekom",
    "location": "Mostar",
    "description": "Lorem ipsum dolor sit amet, consectetur adipiscing elit. Curabitur et ligula.",
    "qualificationsAndRequirements": "Lorem ipsum dolor sit amet, consectetur adipiscing elit.",
    "tags": ["IoT", "Smart Cities", "5G"],
    "experienceRequired": "Not required",
    "engagementType": "Flexible",
    "workArrangement": "Remote",
    "endingDate": "2024-12-30",
    "benefits": "Lorem ipsum dolor sit amet, consectetur adipiscing elit.",
    "employeeInfo": "Lorem ipsum dolor sit amet, consectetur adipiscing elit.",
    "contactPerson": "Alice Brown",
    "contactPersonEmail": "alice.brown@telekom.com"
  },
  {
    "id": 4,
    "type": "Mentorship",
    "fieldOfStudy": "Media and Communication",
    "title": "Digital Marketing Strategy",
    "company": "Deutsche Telekom",
    "location": "Hamburg",
    "description": "Lorem ipsum dolor sit amet, consectetur adipiscing elit. Aenean sit amet nulla.",
    "qualificationsAndRequirements": "Lorem ipsum dolor sit amet, consectetur adipiscing elit.",
    "tags": ["SEO", "Content Marketing", "Google Analytics"],
    "experienceRequired": "Junior",
    "engagementType": "Part-time",
    "workArrangement": "On-site",
    "endingDate": "2025-03-01",
    "benefits": "Lorem ipsum dolor sit amet, consectetur adipiscing elit.",
    "employeeInfo": "Lorem ipsum dolor sit amet, consectetur adipiscing elit.",
    "contactPerson": "Emily Green",
    "contactPersonEmail": "emily.green@telekom.com"
  },
  {
    "id": 5,
    "type": "Job Offer",
    "fieldOfStudy": "Computer Sciences and Engineering",
    "title": "Backend Developer",
    "company": "Deutsche Telekom",
    "location": "Munich",
    "description": "Lorem ipsum dolor sit amet, consectetur adipiscing elit. Quisque fringilla.",
    "qualificationsAndRequirements": "Lorem ipsum dolor sit amet, consectetur adipiscing elit.",
    "tags": ["Node.js", "SQL", "API Development"],
    "experienceRequired": ["Medior", "Senior"],
    "engagementType": "Full-time",
    "workArrangement": "Hybrid",
    "endingDate": "2025-02-20",
    "benefits": "Lorem ipsum dolor sit amet, consectetur adipiscing elit.",
    "employeeInfo": "Lorem ipsum dolor sit amet, consectetur adipiscing elit.",
    "contactPerson": "Robert White",
    "contactPersonEmail": "robert.white@telekom.com"
  },
  {
    "id": 6,
    "type": "Extra Curriculum Project",
    "fieldOfStudy": "Visual Arts and Visual Communications Design",
    "title": "Augmented Reality Interfaces",
    "company": "Deutsche Telekom",
    "location": "Berlin",
    "description": "Lorem ipsum dolor sit amet, consectetur adipiscing elit. Vestibulum vehicula.",
    "qualificationsAndRequirements": "Lorem ipsum dolor sit amet, consectetur adipiscing elit.",
    "tags": ["AR", "Unity", "UX Design"],
    "experienceRequired": "Intermediate",
    "engagementType": "Project-based",
    "workArrangement": "Remote",
    "endingDate": "2024-12-10",
    "benefits": "Lorem ipsum dolor sit amet, consectetur adipiscing elit.",
    "employeeInfo": "Lorem ipsum dolor sit amet, consectetur adipiscing elit.",
    "contactPerson": "Anna Williams",
    "contactPersonEmail": "anna.williams@telekom.com"
  },
  {
    "id": 7,
    "type": "Job Offer",
    "fieldOfStudy": "Genetics and Bioengineering",
    "title": "Bioinformatics Specialist",
    "company": "Deutsche Telekom",
    "location": "Frankfurt",
    "description": "Lorem ipsum dolor sit amet, consectetur adipiscing elit. Praesent at risus.",
    "qualificationsAndRequirements": "Lorem ipsum dolor sit amet, consectetur adipiscing elit.",
    "tags": ["Bioinformatics", "Python", "R"],
    "experienceRequired": "Senior",
    "engagementType": "Full-time",
    "workArrangement": "Hybrid",
    "endingDate": "2024-12-15",
    "benefits": "Lorem ipsum dolor sit amet, consectetur adipiscing elit.",
    "employeeInfo": "Lorem ipsum dolor sit amet, consectetur adipiscing elit.",
    "contactPerson": "Laura Clarke",
    "contactPersonEmail": "laura.clarke@telekom.com"
  },
  {
    "id": 8,
    "type": "Internship",
    "fieldOfStudy": "Mechanical Engineering",
    "title": "Robotics Intern",
    "company": "Deutsche Telekom",
    "location": "Cologne",
    "description": "Lorem ipsum dolor sit amet, consectetur adipiscing elit. Fusce accumsan.",
    "qualificationsAndRequirements": "Lorem ipsum dolor sit amet, consectetur adipiscing elit.",
    "tags": ["Robotics", "CAD", "Automation"],
    "experienceRequired": "Intern",
    "engagementType": "Part-time",
    "workArrangement": "On-site",
    "endingDate": "2025-02-01",
    "benefits": "Lorem ipsum dolor sit amet, consectetur adipiscing elit.",
    "employeeInfo": "Lorem ipsum dolor sit amet, consectetur adipiscing elit.",
    "contactPerson": "Kevin Martin",
    "contactPersonEmail": "kevin.martin@telekom.com"
  },
  {
    "id": 9,
    "type": "Mentorship",
    "fieldOfStudy": "Artificial Intelligence and Data Engineering",
    "title": "AI Ethics and Applications",
    "company": "Deutsche Telekom",
    "location": "Berlin",
    "description": "Lorem ipsum dolor sit amet, consectetur adipiscing elit. Sed scelerisque.",
    "qualificationsAndRequirements": "Lorem ipsum dolor sit amet, consectetur adipiscing elit.",
    "tags": ["Ethical AI", "Data Privacy", "Machine Learning"],
    "experienceRequired": "N/A",
    "engagementType": "Part-time",
    "workArrangement": "Remote",
    "endingDate": "2025-02-30",
    "benefits": "Lorem ipsum dolor sit amet, consectetur adipiscing elit.",
    "employeeInfo": "Lorem ipsum dolor sit amet, consectetur adipiscing elit.",
    "contactPerson": "Sarah Taylor",
    "contactPersonEmail": "sarah.taylor@telekom.com"
  },
  {
    "id": 10,
    "type": "Thesis Topic",
    "fieldOfStudy": "Electrical and Electronics Engineering",
    "title": "Wireless Charging Systems",
    "company": "Deutsche Telekom",
    "location": "Stuttgart",
    "description": "Lorem ipsum dolor sit amet, consectetur adipiscing elit. Ut sodales.",
    "qualificationsAndRequirements": "Lorem ipsum dolor sit amet, consectetur adipiscing elit.",
    "tags": ["Wireless", "Charging", "Electronics"],
    "experienceRequired": "N/A",
    "engagementType": "Flexible",
    "workArrangement": "Remote",
    "endingDate": "2024-09-30",
    "benefits": "Lorem ipsum dolor sit amet, consectetur adipiscing elit.",
    "employeeInfo": "Lorem ipsum dolor sit amet, consectetur adipiscing elit.",
    "contactPerson": "David Johnson",
    "contactPersonEmail": "david.johnson@telekom.com"
  },
  {
    "id": 11,
    "type": "Extra Curriculum Project",
    "fieldOfStudy": "Software Engineering",
    "title": "Open Source Contribution",
    "company": "Deutsche Telekom",
    "location": "Berlin",
    "description": "Lorem ipsum dolor sit amet, consectetur adipiscing elit. Nullam tincidunt.",
    "qualificationsAndRequirements": "Lorem ipsum dolor sit amet, consectetur adipiscing elit.",
    "tags": ["Open Source", "Git", "Telecom"],
    "experienceRequired": "Intermediate",
    "engagementType": "Project-based",
    "workArrangement": "Remote",
    "endingDate": "2025-01-20",
    "benefits": "Lorem ipsum dolor sit amet, consectetur adipiscing elit.",
    "employeeInfo": "Lorem ipsum dolor sit amet, consectetur adipiscing elit.",
    "contactPerson": "Sophia Lee",
    "contactPersonEmail": "sophia.lee@telekom.com"
  },
  {
    "id": 12,
    "type": "Job Offer",
    "fieldOfStudy": "Artificial Intelligence and Data Engineering",
    "title": "Machine Learning Engineer",
    "company": "Deutsche Telekom",
    "location": "Berlin",
    "description": "Lorem ipsum dolor sit amet, consectetur adipiscing elit. Vivamus blandit.",
    "qualificationsAndRequirements": "Lorem ipsum dolor sit amet, consectetur adipiscing elit.",
    "tags": ["Machine Learning", "TensorFlow", "Data Pipelines"],
    "experienceRequired": ["Medior", "Senior"],
    "engagementType": "Full-time",
    "workArrangement": "Hybrid",
    "endingDate": "2025-03-10",
    "benefits": "Lorem ipsum dolor sit amet, consectetur adipiscing elit.",
    "employeeInfo": "Lorem ipsum dolor sit amet, consectetur adipiscing elit.",
    "contactPerson": "Mark Allen",
    "contactPersonEmail": "mark.allen@telekom.com"
  },
  {
    "id": 13,
    "type": "Internship",
    "fieldOfStudy": "Mechanical Engineering",
    "title": "Automation Intern",
    "company": "Deutsche Telekom",
    "location": "Cologne",
    "description": "Lorem ipsum dolor sit amet, consectetur adipiscing elit. Maecenas posuere.",
    "qualificationsAndRequirements": "Lorem ipsum dolor sit amet, consectetur adipiscing elit.",
    "tags": ["Automation", "Robotics", "System Design"],
    "experienceRequired": "Intern",
    "engagementType": "Part-time",
    "workArrangement": "On-site",
    "endingDate": "2025-02-01",
    "benefits": "Lorem ipsum dolor sit amet, consectetur adipiscing elit.",
    "employeeInfo": "Lorem ipsum dolor sit amet, consectetur adipiscing elit.",
    "contactPerson": "Liam Brown",
    "contactPersonEmail": "liam.brown@telekom.com"
  },
  {
    "id": 14,
    "type": "Mentorship",
    "fieldOfStudy": "Visual Arts and Visual Communications Design",
    "title": "UI/UX Design Principles",
    "company": "Deutsche Telekom",
    "location": "Hamburg",
    "description": "Lorem ipsum dolor sit amet, consectetur adipiscing elit. Quisque commodo.",
    "qualificationsAndRequirements": "Lorem ipsum dolor sit amet, consectetur adipiscing elit.",
    "tags": ["UI/UX", "Design Systems", "Prototyping"],
    "experienceRequired": "N/A",
    "engagementType": "Part-time",
    "workArrangement": "Remote",
    "endingDate": "2025-01-15",
    "benefits": "Lorem ipsum dolor sit amet, consectetur adipiscing elit.",
    "employeeInfo": "Lorem ipsum dolor sit amet, consectetur adipiscing elit.",
    "contactPerson": "Olivia White",
    "contactPersonEmail": "olivia.white@telekom.com"
  }
]
